fluidai_mcp/__init__.py
fluidai_mcp/cli.py
fluidai_mcp/services/__init__.py
fluidai_mcp/services/env_manager.py
fluidai_mcp/services/mcp_remote_client.py
fluidai_mcp/services/network_utils.py
fluidai_mcp/services/package_installer.py
fluidai_mcp/services/package_launcher.py
fluidai_mcp/services/package_list.py
fluidai_mcp/services/s3_utils.py
fluidai_mcp/services/utils/__init__.py
fluidai_mcp/services/utils/mcp_session.py
fluidai_mcp/services/utils/npm_utils.py
fmcp_trial_atharva-1.1.1.dist-info/licenses/LICENSE
fmcp_trial_atharva-1.1.1.dist-info/METADATA
fmcp_trial_atharva-1.1.1.dist-info/WHEEL
fmcp_trial_atharva-1.1.1.dist-info/entry_points.txt
fmcp_trial_atharva-1.1.1.dist-info/top_level.txt
fmcp_trial_atharva-1.1.1.dist-info/RECORD
