Metadata-Version: 2.4
Name: fmcp-trial-atharva
Version: 1.1.1
Summary: FluidMCP - Universal MCP server launcher and remote client (Trial Version)
Home-page: https://github.com/Fluid-AI/fluidmcp
Author: Fluid AI
Author-email: Atharva Nawadkar <atharva.n@trutech.org>
License: MIT
Project-URL: Homepage, https://github.com/yourusername/fluidmcp
Project-URL: Documentation, https://github.com/yourusername/fluidmcp#readme
Project-URL: Repository, https://github.com/yourusername/fluidmcp
Project-URL: Issues, https://github.com/yourusername/fluidmcp/issues
Keywords: mcp,model-context-protocol,ai,tools,trial
Classifier: Development Status :: 4 - Beta
Classifier: Intended Audience :: Developers
Classifier: License :: OSI Approved :: MIT License
Classifier: Programming Language :: Python :: 3
Classifier: Programming Language :: Python :: 3.8
Classifier: Programming Language :: Python :: 3.9
Classifier: Programming Language :: Python :: 3.10
Classifier: Programming Language :: Python :: 3.11
Classifier: Programming Language :: Python :: 3.12
Requires-Python: >=3.6
License-File: LICENSE
Requires-Dist: aiohttp>=3.8.0
Requires-Dist: fastapi>=0.100.0
Requires-Dist: uvicorn>=0.20.0
Requires-Dist: loguru>=0.7.0
Requires-Dist: boto3>=1.26.0
Requires-Dist: requests>=2.28.0
Requires-Dist: psutil>=5.9.0
Requires-Dist: pydantic>=2.0.0
Requires-Dist: click>=8.0.0
Requires-Dist: httpx>=0.24.0
Requires-Dist: sse-starlette>=2.0.0
Provides-Extra: dev
Requires-Dist: pytest>=7.0; extra == "dev"
Requires-Dist: black>=22.0; extra == "dev"
Requires-Dist: flake8>=4.0; extra == "dev"
Requires-Dist: twine>=4.0; extra == "dev"
Requires-Dist: build>=0.8; extra == "dev"
Dynamic: author
Dynamic: home-page
Dynamic: license-file
Dynamic: requires-python
